odoo/addons/helpdesk_mgmt_assign_method/README.rst
odoo/addons/helpdesk_mgmt_assign_method/__init__.py
odoo/addons/helpdesk_mgmt_assign_method/__manifest__.py
odoo/addons/helpdesk_mgmt_assign_method/i18n/helpdesk_mgmt_assign_method.pot
odoo/addons/helpdesk_mgmt_assign_method/i18n/it.po
odoo/addons/helpdesk_mgmt_assign_method/models/__init__.py
odoo/addons/helpdesk_mgmt_assign_method/models/helpdesk_ticket.py
odoo/addons/helpdesk_mgmt_assign_method/models/helpdesk_ticket_team.py
odoo/addons/helpdesk_mgmt_assign_method/readme/CONTRIBUTORS.md
odoo/addons/helpdesk_mgmt_assign_method/readme/DESCRIPTION.md
odoo/addons/helpdesk_mgmt_assign_method/readme/USAGE.md
odoo/addons/helpdesk_mgmt_assign_method/static/description/icon.png
odoo/addons/helpdesk_mgmt_assign_method/static/description/index.html
odoo/addons/helpdesk_mgmt_assign_method/tests/__init__.py
odoo/addons/helpdesk_mgmt_assign_method/tests/test_helpdesk_ticket_assign.py
odoo/addons/helpdesk_mgmt_assign_method/views/helpdesk_ticket_team.xml
odoo_addon_helpdesk_mgmt_assign_method-17.0.1.0.0.2.dist-info/METADATA
odoo_addon_helpdesk_mgmt_assign_method-17.0.1.0.0.2.dist-info/WHEEL
odoo_addon_helpdesk_mgmt_assign_method-17.0.1.0.0.2.dist-info/top_level.txt
odoo_addon_helpdesk_mgmt_assign_method-17.0.1.0.0.2.dist-info/RECORD
